{
  "questionnaires": [
    {
      "id": 1,
      "title": "GoTech Questionnaire",
      "subtitle": "Show me what you got!",
      "questions": [
        {
          "id": 123,
          "required": false,
          "type": "multipleChoice",
          "title": "What language is your favourite?",
          "options": [
            {
              "type": "closed",
              "caption": "Kotlin"
            },
            {
              "type": "closed",
              "caption": "Java"
            },
            {
              "type": "closed",
              "caption": "C++"
            },
            {
              "type": "closed",
              "caption": "C#"
            }
          ]
        },
        {
          "id": 200,
          "required": false,
          "type": "open",
          "title": "What do you like about programming?",
          "hint": "Your answer"
        },
        {
          "id": 300,
          "required": false,
          "type": "multipleChoice",
          "title": "How was the assignment?",
          "options": [
            {
              "type": "closed",
              "caption": "Easy"
            },
            {
              "type": "closed",
              "caption": "Normal"
            },
            {
              "type": "closed",
              "caption": "Hard"
            },
            {
              "type": "open",
              "caption": "Other:"
            }
          ]
        }
      ]
    }
  ],
  "answers": [
    {
      "questionnaireId": 1,
      "answers": [
        {
          "questionId": 123,
          "body": "C#"
        },
        {
          "questionId": 200,
          "body": "Learning new things"
        },
        {
          "questionId": 300,
          "body": "Normal"
        }
      ],
      "id": 1
    }
  ]
}